visor/__init__.py
visor/image.py
visor/roi.py
visor/transform.py
visor/vsr.py
visor/tests/test_image.py
visor/tests/test_roi.py
visor/tests/test_transform.py
visor/tests/test_vsr.py
visor_py-2025.8.1.post2.dist-info/licenses/LICENSE
visor_py-2025.8.1.post2.dist-info/METADATA
visor_py-2025.8.1.post2.dist-info/WHEEL
visor_py-2025.8.1.post2.dist-info/top_level.txt
visor_py-2025.8.1.post2.dist-info/RECORD
