Metadata-Version: 2.4
Name: visor-py
Version: 2025.8.1.post2
Summary: A Python Library for VISoR Image.
Author-email: Zijian Yi <arrowzeke@gmail.com>, Eddy Xiao <bewantbe@gmail.com>
License: BSD
Project-URL: Repository, https://github.com/visor-tech/visor-py
Keywords: VISoR
Classifier: Programming Language :: Python :: 3
Classifier: License :: OSI Approved :: BSD License
Requires-Python: >=3.11
License-File: LICENSE
Requires-Dist: zarr<4,>=3
Requires-Dist: zarrs>=0.1.4
Requires-Dist: numcodecs>=0.16
Requires-Dist: simpleitk>=2.5.2
Dynamic: license-file
